last_shout/__init__.py
last_shout/libshout/__init__.py
last_shout/libshout/lastfm.py
last_shout/libshout/options.py
last_shout/libshout/settings.py
last_shout/libshout/utils.py
last_shout/main.py
last_shout-0.9.0.dist-info/LICENSE
last_shout-0.9.0.dist-info/METADATA
last_shout-0.9.0.dist-info/WHEEL
last_shout-0.9.0.dist-info/entry_points.txt
last_shout-0.9.0.dist-info/RECORD
