Metadata-Version: 2.3
Name: last-shout
Version: 0.9.0
Summary: Post Last.fm statistics to Twitter and/or Mastodon
License: GPL-3.0-or-later
Keywords: lastfm,twitter,python,music,mastodon
Author: Brian Pepple
Author-email: bdpepple@gmail.com
Maintainer: Brian Pepple
Maintainer-email: bdpepple@gmail.com
Requires-Python: >=3.11,<3.14
Classifier: Development Status :: 4 - Beta
Classifier: Environment :: Console
Classifier: Intended Audience :: End Users/Desktop
Classifier: License :: OSI Approved :: GNU General Public License v3 or later (GPLv3+)
Classifier: Natural Language :: English
Classifier: Operating System :: MacOS :: MacOS X
Classifier: Operating System :: Microsoft :: Windows
Classifier: Operating System :: POSIX
Classifier: Operating System :: POSIX :: BSD
Classifier: Operating System :: POSIX :: Linux
Classifier: Programming Language :: Python :: 3
Classifier: Programming Language :: Python :: 3.11
Classifier: Programming Language :: Python :: 3.12
Classifier: Programming Language :: Python :: 3.13
Classifier: Topic :: Other/Nonlisted Topic
Classifier: Topic :: Utilities
Requires-Dist: Mastodon.py (>=1.5.1,<2.0.0)
Requires-Dist: atproto (>=0.0.57,<0.0.58)
Requires-Dist: pylast (>=5.3.0,<6.0.0)
Requires-Dist: pyxdg (>=0.28,<0.29)
Project-URL: Bug Tracker, https://github.com/bpepple/last-shout/issues
Project-URL: Homepage, https://github.com/bpepple/last-shout
